sphinxcontrib_autoprogram-0.1.9-py3.12-nspkg.pth
sphinxcontrib/autoprogram.py
sphinxcontrib_autoprogram-0.1.9.dist-info/LICENSE
sphinxcontrib_autoprogram-0.1.9.dist-info/METADATA
sphinxcontrib_autoprogram-0.1.9.dist-info/WHEEL
sphinxcontrib_autoprogram-0.1.9.dist-info/namespace_packages.txt
sphinxcontrib_autoprogram-0.1.9.dist-info/top_level.txt
sphinxcontrib_autoprogram-0.1.9.dist-info/RECORD
